smartpaste/__init__.py
smartpaste/smartpaste.py
smartpaste-0.1.2.dist-info/licenses/LICENSE
smartpaste-0.1.2.dist-info/METADATA
smartpaste-0.1.2.dist-info/WHEEL
smartpaste-0.1.2.dist-info/top_level.txt
smartpaste-0.1.2.dist-info/RECORD
