Metadata-Version: 2.4
Name: smartpaste
Version: 0.1.2
Summary: Reliable cross-platform clipboard pasting for Python.
Author-email: Alex M <alexmalone489@gmail.com>
License-Expression: MIT
Project-URL: Homepage, https://github.com/AMAMazing/smartpaste
Project-URL: Bug Tracker, https://github.com/AMAMazing/smartpaste/issues
Project-URL: Repository, https://github.com/AMAMazing/smartpaste
Keywords: smartpaste,paste,automation,gui,pyautogui,pyperclip,emoji,clipboard
Classifier: Programming Language :: Python :: 3
Classifier: Operating System :: OS Independent
Classifier: Topic :: Software Development :: Libraries :: Python Modules
Classifier: Topic :: Utilities
Classifier: Intended Audience :: Developers
Requires-Python: >=3.7
License-File: LICENSE
Requires-Dist: pyperclip>=1.8.2
Requires-Dist: PyAutoGUI>=0.9.53
Dynamic: license-file
